{
  "$schema": "https://developer.microsoft.com/json-schemas/fabric/item/report/definition/visualContainer/2.7.0/schema.json",
  "name": "fb_kpi3",
  "position": {
    "x": 430.90909090909088,
    "y": 68.181818181818173,
    "z": 12000,
    "height": 78.181818181818173,
    "width": 204.54545454545453,
    "tabOrder": 12000
  },
  "visual": {
    "visualType": "card",
    "query": {
      "queryState": {
        "Values": {
          "projections": [
            {
              "field": {
                "Measure": {
                  "Expression": {
                    "SourceRef": {
                      "Entity": "00_Médidas"
                    }
                  },
                  "Property": "FB Saldo Seguidores"
                }
              },
              "queryRef": "00_Médidas.FB Saldo Seguidores"
            }
          ]
        }
      }
    },
    "objects": {
      "labels": [
        {
          "properties": {
            "color": {
              "solid": {
                "color": {
                  "expr": {
                    "Literal": {
                      "Value": "'#F0F6FC'"
                    }
                  }
                }
              }
            },
            "fontSize": {
              "expr": {
                "Literal": {
                  "Value": "22D"
                }
              }
            },
            "bold": {
              "expr": {
                "Literal": {
                  "Value": "true"
                }
              }
            }
          }
        }
      ],
      "categoryLabels": [
        {
          "properties": {
            "color": {
              "solid": {
                "color": {
                  "expr": {
                    "Literal": {
                      "Value": "'#1877F2'"
                    }
                  }
                }
              }
            },
            "fontSize": {
              "expr": {
                "Literal": {
                  "Value": "11D"
                }
              }
            },
            "bold": {
              "expr": {
                "Literal": {
                  "Value": "true"
                }
              }
            }
          }
        }
      ]
    },
    "visualContainerObjects": {
      "title": [
        {
          "properties": {
            "bold": {
              "expr": {
                "Literal": {
                  "Value": "true"
                }
              }
            }
          }
        }
      ]
    }
  },
  "filterConfig": {
    "filters": [
      {
        "name": "e1a4bdccb1930c056c1c",
        "field": {
          "Measure": {
            "Expression": {
              "SourceRef": {
                "Entity": "00_Médidas"
              }
            },
            "Property": "FB Saldo Seguidores"
          }
        },
        "type": "Advanced"
      }
    ]
  }
}