{
  "$schema": "https://developer.microsoft.com/json-schemas/fabric/item/report/definition/visualContainer/2.7.0/schema.json",
  "name": "tab_campanhas_meta",
  "position": {
    "x": -2000,
    "y": -2000,
    "z": 12000,
    "height": 215,
    "width": 627,
    "tabOrder": 12000
  },
  "visual": {
    "visualType": "tableEx",
    "query": {
      "queryState": {
        "Values": {
          "projections": [
            {
              "field": {
                "Column": {
                  "Expression": {
                    "SourceRef": {
                      "Entity": "Meta_Ads_Campanhas"
                    }
                  },
                  "Property": "campaign_name"
                }
              },
              "queryRef": "Meta_Ads_Campanhas.campaign_name",
              "nativeQueryRef": "campaign_name"
            },
            {
              "field": {
                "Measure": {
                  "Expression": {
                    "SourceRef": {
                      "Entity": "00_Médidas"
                    }
                  },
                  "Property": "Meta Investimento Total"
                }
              },
              "queryRef": "00_Médidas.Meta Investimento Total",
              "nativeQueryRef": "Meta Investimento Total"
            },
            {
              "field": {
                "Measure": {
                  "Expression": {
                    "SourceRef": {
                      "Entity": "00_Médidas"
                    }
                  },
                  "Property": "Total Conversões Ads"
                }
              },
              "queryRef": "00_Médidas.Total Conversões Ads",
              "nativeQueryRef": "Total Conversões Ads"
            },
            {
              "field": {
                "Measure": {
                  "Expression": {
                    "SourceRef": {
                      "Entity": "00_Médidas"
                    }
                  },
                  "Property": "ROAS Conversão Ads"
                }
              },
              "queryRef": "00_Médidas.ROAS Conversão Ads",
              "nativeQueryRef": "ROAS Conversão Ads"
            },
            {
              "field": {
                "Measure": {
                  "Expression": {
                    "SourceRef": {
                      "Entity": "00_Médidas"
                    }
                  },
                  "Property": "CPA Ads"
                }
              },
              "queryRef": "00_Médidas.CPA Ads",
              "nativeQueryRef": "CPA Ads"
            }
          ]
        }
      }
    },
    "objects": {
      "general": [
        {
          "properties": {}
        }
      ],
      "grid": [
        {
          "properties": {
            "gridVertical": {
              "expr": {
                "Literal": {
                  "Value": "false"
                }
              }
            },
            "gridHorizontalColor": {
              "solid": {
                "color": {
                  "expr": {
                    "Literal": {
                      "Value": "'#30363D'"
                    }
                  }
                }
              }
            },
            "rowPadding": {
              "expr": {
                "Literal": {
                  "Value": "3D"
                }
              }
            },
            "outlineColor": {
              "solid": {
                "color": {
                  "expr": {
                    "Literal": {
                      "Value": "'#30363D'"
                    }
                  }
                }
              }
            }
          }
        }
      ],
      "columnHeaders": [
        {
          "properties": {
            "fontColor": {
              "solid": {
                "color": {
                  "expr": {
                    "Literal": {
                      "Value": "'#94A3B8'"
                    }
                  }
                }
              }
            },
            "backColor": {
              "solid": {
                "color": {
                  "expr": {
                    "Literal": {
                      "Value": "'#0D1117'"
                    }
                  }
                }
              }
            },
            "fontSize": {
              "expr": {
                "Literal": {
                  "Value": "9D"
                }
              }
            }
          }
        }
      ]
    }
  }
}